LICENSE.txt
MANIFEST.in
README.md
flint.py
setup.py
flint_md.egg-info/PKG-INFO
flint_md.egg-info/SOURCES.txt
flint_md.egg-info/dependency_links.txt
flint_md.egg-info/requires.txt
flint_md.egg-info/top_level.txt