Metadata-Version: 1.0
Name: flint-md
Version: 1.1.1
Summary: Dynamic Markdown Templating
Home-page: http://cdawson.net/flint
Author: Charles Dawson
Author-email: charles.dwsn@gmail.com
License: MIT License
Download-URL: http://github.com/TheBritKnight/Flint
Platform: UNKNOWN
Classifier: License :: OSI Approved :: MIT License
Classifier: Programming Language :: Python
Classifier: Programming Language :: Python :: 3
Classifier: Operating System :: OS Independent
Classifier: Topic :: Text Processing :: Markup
Classifier: Topic :: Internet :: WWW/HTTP :: Dynamic Content
Classifier: Intended Audience :: Developers
Classifier: Environment :: Web Environment
